graphene_plugin.py
graphene_typing.py
graphene-stubs/__init__.pyi
graphene-stubs/pyutils/__init__.pyi
graphene-stubs/pyutils/compat.pyi
graphene-stubs/pyutils/init_subclass.pyi
graphene-stubs/pyutils/signature.pyi
graphene-stubs/pyutils/version.pyi
graphene-stubs/relay/__init__.pyi
graphene-stubs/relay/connection.pyi
graphene-stubs/relay/mutation.pyi
graphene-stubs/relay/node.pyi
graphene-stubs/relay/tests/__init__.pyi
graphene-stubs/relay/tests/test_connection.pyi
graphene-stubs/relay/tests/test_connection_query.pyi
graphene-stubs/relay/tests/test_global_id.pyi
graphene-stubs/relay/tests/test_mutation.pyi
graphene-stubs/relay/tests/test_node.pyi
graphene-stubs/relay/tests/test_node_custom.pyi
graphene-stubs/test/__init__.pyi
graphene-stubs/tests/__init__.pyi
graphene-stubs/tests/issues/__init__.pyi
graphene-stubs/tests/issues/test_313.pyi
graphene-stubs/tests/issues/test_356.pyi
graphene-stubs/tests/issues/test_425.pyi
graphene-stubs/tests/issues/test_490.pyi
graphene-stubs/tests/issues/test_720.pyi
graphene-stubs/tests/issues/test_956.pyi
graphene-stubs/types/__init__.pyi
graphene-stubs/types/abstracttype.pyi
graphene-stubs/types/argument.pyi
graphene-stubs/types/base.pyi
graphene-stubs/types/context.pyi
graphene-stubs/types/datetime.pyi
graphene-stubs/types/decimal.pyi
graphene-stubs/types/definitions.pyi
graphene-stubs/types/dynamic.pyi
graphene-stubs/types/enum.pyi
graphene-stubs/types/field.pyi
graphene-stubs/types/generic.pyi
graphene-stubs/types/inputfield.pyi
graphene-stubs/types/inputobjecttype.pyi
graphene-stubs/types/interface.pyi
graphene-stubs/types/json.pyi
graphene-stubs/types/mountedtype.pyi
graphene-stubs/types/mutation.pyi
graphene-stubs/types/objecttype.pyi
graphene-stubs/types/resolver.pyi
graphene-stubs/types/scalars.pyi
graphene-stubs/types/schema.pyi
graphene-stubs/types/structures.pyi
graphene-stubs/types/typemap.pyi
graphene-stubs/types/union.pyi
graphene-stubs/types/unmountedtype.pyi
graphene-stubs/types/utils.pyi
types_graphene-0.22.dist-info/LICENSE
types_graphene-0.22.dist-info/METADATA
types_graphene-0.22.dist-info/WHEEL
types_graphene-0.22.dist-info/top_level.txt
types_graphene-0.22.dist-info/RECORD
