Metadata-Version: 2.1
Name: types-graphene
Version: 0.22
Summary: Graphene stubs and mypy plugin
Home-page: https://github.com/dongzoolee/types-graphene
Author: dongzoolee
Author-email: me@leed.at
License: MIT License
Classifier: Programming Language :: Python :: 3
Classifier: License :: OSI Approved :: MIT License
License-File: LICENSE
Requires-Dist: mypy (>=0.750)
Requires-Dist: typing-extensions (>=3.6.5)
